test/__init__.py
test/fakes.py
test/test_tripleo_get_hash.py
test/test_tripleo_get_hash_info.py
tripleo_get_hash/__init__.py
tripleo_get_hash/__main__.py
tripleo_get_hash/constants.py
tripleo_get_hash/exceptions.py
tripleo_get_hash/tripleo_hash_info.py
tripleo_get_hash-0.1.1.dev37.data/data/share/ansible/plugins/modules/tripleo_get_hash.py
usr/local/etc/tripleo_get_hash/config.yaml
tripleo_get_hash-0.1.1.dev37.dist-info/LICENSE
tripleo_get_hash-0.1.1.dev37.dist-info/METADATA
tripleo_get_hash-0.1.1.dev37.dist-info/WHEEL
tripleo_get_hash-0.1.1.dev37.dist-info/entry_points.txt
tripleo_get_hash-0.1.1.dev37.dist-info/pbr.json
tripleo_get_hash-0.1.1.dev37.dist-info/top_level.txt
tripleo_get_hash-0.1.1.dev37.dist-info/RECORD
